langflow_toon/__init__.py
langflow_toon/components/__init__.py
langflow_toon/components/toon_component.py
langflow_toon/config/__init__.py
langflow_toon/config/constants.py
langflow_toon/converters/__init__.py
langflow_toon/converters/base.py
langflow_toon/converters/csv_converter.py
langflow_toon/converters/html_converter.py
langflow_toon/converters/json_converter.py
langflow_toon/converters/xml_converter.py
langflow_toon/core/__init__.py
langflow_toon/core/toon_converter.py
langflow_toon/detectors/__init__.py
langflow_toon/detectors/format_detector.py
langflow_toon/models/__init__.py
langflow_toon/models/data.py
langflow_toon/models/errors.py
langflow_toon/utils/__init__.py
langflow_toon/utils/error_formatter.py
langflow_toon/utils/memory_estimator.py
langflow_toon/utils/token_counter.py
langflow_toon/utils/toon_encoder.py
langflow_toon/validators/__init__.py
langflow_toon/validators/input_validator.py
langflow_toon/validators/toon_validator.py
langflow_toon-0.1.2.dist-info/METADATA
langflow_toon-0.1.2.dist-info/WHEEL
langflow_toon-0.1.2.dist-info/top_level.txt
langflow_toon-0.1.2.dist-info/RECORD
