Metadata-Version: 2.4
Name: langflow-toon
Version: 0.1.2
Summary: TOON (Token-Oriented Object Notation) converter component for Langflow
Author: Langflow TOON Contributors
License: MIT
Project-URL: Homepage, https://github.com/toon-format/toon
Project-URL: Repository, https://github.com/toon-format/toon
Project-URL: Issues, https://github.com/toon-format/toon/issues
Keywords: langflow,toon,llm,token-optimization,data-format
Classifier: Development Status :: 3 - Alpha
Classifier: Intended Audience :: Developers
Classifier: License :: OSI Approved :: MIT License
Classifier: Programming Language :: Python :: 3
Classifier: Programming Language :: Python :: 3.10
Classifier: Programming Language :: Python :: 3.11
Classifier: Programming Language :: Python :: 3.12
Classifier: Topic :: Software Development :: Libraries :: Python Modules
Requires-Python: >=3.10
Requires-Dist: tiktoken>=0.5.0
Requires-Dist: xmltodict>=0.13.0
Provides-Extra: dev
Requires-Dist: pytest>=7.0.0; extra == "dev"
Requires-Dist: pytest-cov>=4.0.0; extra == "dev"
